odoo/addons/sale_order_product_picker/README.rst
odoo/addons/sale_order_product_picker/__init__.py
odoo/addons/sale_order_product_picker/__manifest__.py
odoo/addons/sale_order_product_picker/hooks.py
odoo/addons/sale_order_product_picker/i18n/es.po
odoo/addons/sale_order_product_picker/i18n/it.po
odoo/addons/sale_order_product_picker/i18n/sale_order_product_picker.pot
odoo/addons/sale_order_product_picker/models/__init__.py
odoo/addons/sale_order_product_picker/models/ir_config_parameter.py
odoo/addons/sale_order_product_picker/models/sale_order.py
odoo/addons/sale_order_product_picker/models/sale_order_picker.py
odoo/addons/sale_order_product_picker/readme/CONFIGURE.rst
odoo/addons/sale_order_product_picker/readme/CONTRIBUTORS.rst
odoo/addons/sale_order_product_picker/readme/DESCRIPTION.rst
odoo/addons/sale_order_product_picker/readme/USAGE.rst
odoo/addons/sale_order_product_picker/security/ir.model.access.csv
odoo/addons/sale_order_product_picker/static/description/icon.png
odoo/addons/sale_order_product_picker/static/description/index.html
odoo/addons/sale_order_product_picker/static/image/picker.gif
odoo/addons/sale_order_product_picker/static/src/form/form_controller.esm.js
odoo/addons/sale_order_product_picker/static/src/kanban/kanban_record.esm.js
odoo/addons/sale_order_product_picker/static/src/scss/picker.scss
odoo/addons/sale_order_product_picker/static/src/utils/picker_change_processor.esm.js
odoo/addons/sale_order_product_picker/static/src/x2many/x2many_field.esm.js
odoo/addons/sale_order_product_picker/views/product_views.xml
odoo/addons/sale_order_product_picker/views/sale_order_views.xml
odoo_addon_sale_order_product_picker-16.0.1.2.1.dist-info/METADATA
odoo_addon_sale_order_product_picker-16.0.1.2.1.dist-info/WHEEL
odoo_addon_sale_order_product_picker-16.0.1.2.1.dist-info/top_level.txt
odoo_addon_sale_order_product_picker-16.0.1.2.1.dist-info/RECORD
